Workbook
Name Clasificacion: Validaciones!$B$2:$B$35
Name Partida: Validaciones!$C$2:$C$35
Name SS: Validaciones!$A$2:$A$35

Sheet 1_Resumen
C1: DEPARTAMENTO DE MONITOREO DE OBRAS
C3: Informe Técnico Consolidado de Notas de Cambio
A7: Clasificación
A8: Errores de Diseño | D8: =COUNTIF('2_Notas de Cambio'!E:E,A8) -> 1312
A9: Funcionalidad | D9: =COUNTIF('2_Notas de Cambio'!E:E,A9) -> 627
A10: OGUC, SERVIU | D10: =COUNTIF('2_Notas de Cambio'!E:E,A10) -> 0
A11: AS/NTB | D11: =COUNTIF('2_Notas de Cambio'!E:E,A11) -> 223
A12: Total | D12: =SUM(D8:D11) -> 2162
A26: Partidas
A27: Obras Previas | D27: =COUNTIF('2_Notas de Cambio'!F:F,A27) -> 35
A28: Obra Gruesa | D28: =COUNTIF('2_Notas de Cambio'!F:F,A28) -> 398
A29: Terminaciones | D29: =COUNTIF('2_Notas de Cambio'!F:F,A29) -> 732
A30: Instalaciones/Eléctricas | D30: =COUNTIF('2_Notas de Cambio'!F:F,A30) -> 324
A31: Instalaciones/Sanitaria | D31: =COUNTIF('2_Notas de Cambio'!F:F,A31) -> 261
A32: Instalaciones/Gases Clínicos | D32: =COUNTIF('2_Notas de Cambio'!F:F,A32) -> 43
A33: Instalaciones/Climatización | D33: =COUNTIF('2_Notas de Cambio'!F:F,A33) -> 142
A34: Instalaciones/Gas | D34: =COUNTIF('2_Notas de Cambio'!F:F,A34) -> 11
A35: Instalaciones/Control Centralizado | D35: =COUNTIF('2_Notas de Cambio'!F:F,A35) -> 16
A36: Instalaciones/Seguridad | D36: =COUNTIF('2_Notas de Cambio'!F:F,A36) -> 64
A37: Instalaciones/Ascensores | D37: =COUNTIF('2_Notas de Cambio'!F:F,A37) -> 4
A38: Instalaciones/Corrientes Débiles | D38: =COUNTIF('2_Notas de Cambio'!F:F,A38) -> 81
A39: Obras Exteriores | D39: =COUNTIF('2_Notas de Cambio'!F:F,A39) -> 66
A40: Total | D40: =SUM(D27:D39) -> 2177

Sheet 2_Notas de Cambio
A1: SERVICIO DE SALUD | B1: NOMBRE DEL PROYECTO | C1: N° NC | D1: DESCRIPCIÓN | E1: Clasificación | F1: Partida | G1: AUMENTO CON IVA | H1: DISMINUCIÓN CON IVA | I1: OBRA EXTRAORDINARIA CON IVA | J1: SUBTOTAL | K1: AUMENTO DE PLAZO | L1: INDEMNIZACIÓN POR PLAZO CON IVA | M1: TOTAL | N1: ORD DE INGRESO NC SS A MINSAL | O1: C4 MINSAL RESPUESTA A SS | P1: FECHA INGRESO DE NC DEL SS A MINSAL | Q1: VALOR UF (ORD ingreso) | R1: Total UF
A2: 23 Araucanía Norte | B2: Normalizacion Hospital Lonquimay (MOP) | C2: PROYECTO MODIFICADO CLIMATIZACIÓN | D2: Se instalan bombas de recirculación de agua caliente y fría para las instalaciones proyectadas. Bombas centrífugas en base o en línea. Se proyectan coelctores solares térmicos para apoyar el calentamiento del agua sanitaria de modo de disminuir el consumo de gas y/o pellets. | E2: Errores de Diseño | F2: Instalaciones/Eléctricas | G2: 76447354 | H2: 242745203 | I2: 814529295 | J2: =+G2-H2+I2 -> 648231446 | K2: 0 | L2: 0 | M2: =+J2+L2 -> 648231446 | N2: ord. 813 del 06-06-22 | O2: 2259 | P2: 44718 | Q2: 32767.6 | R2: =M2/Q2 -> 19782.695
A3: 23 Araucanía Norte | B3: Normalizacion Hospital Lonquimay (MOP) | C3: PRESUPUESTO MODIFICADO ELÉCTRICO | D3: Misma descripción que mosidifación anterior, pero con observaciones que modifica montos de esta. | E3: Errores de Diseño | F3: Instalaciones/Eléctricas | G3: 17818702 | H3: 439856261 | I3: 826624974 | J3: =+G3-H3+I3 -> 404587415 | K3: 0 | L3: 0 | M3: =+J3+L3 -> 404587415 | N3: ord. 813 del 06-06-22 | O3: 2259 | P3: 44718 | Q3: 32767.6 | R3: =M3/Q3 -> 12347.179
A4: 23 Araucanía Norte | B4: Normalizacion Hospital Lonquimay (MOP) | C4: PRESUPUESTO MODIFICADO ELÉCTRICO | D4: Subestación eléctrica del edificio de 1000KA estará compuesta por un transformador Paud Mounted, con las celdas de conexión a M.T. y B. T. EL transformador trifásico 13.2/0.4 KV refrigerado en silicona. Línea generalizada desde tablero gral. Está definido de acuerdo a estudio desarrollado del proyecto modificado. | E4: Errores de Diseño | F4: Instalaciones/Eléctricas | G4: 61301441 | H4: 324174468 | I4: 1334055899 | J4: =+G4-H4+I4 -> 1071182872 | K4: 0 | L4: 0 | M4: =+J4+L4 -> 1071182872 | N4: ord. 813 del 06-06-22 | O4: 2259 | P4: 44718 | Q4: 32767.6 | R4: =M4/Q4 -> 32690.306
A5: 23 Araucanía Norte | B5: Normalizacion Hospital Lonquimay (MOP) | C5: OBRA EXTRAORDINARIO Nº 58 | D5: ETAPA 3 PROTECCIÓN SOLAR O DE PRIVACIDAD. | E5: AS/NTB | F5: Terminaciones | G5: 25292754 | H5: 0 | I5: 2150407 | J5: =+G5-H5+I5 -> 27443161 | K5: 0 | L5: 0 | M5: =+J5+L5 -> 27443161 | N5: 0rd. 79 del 17-01-23 | O5: 273 | P5: 44943 | Q5: 35239.79 | R5: =M5/Q5 -> 778.75495
A6: 23 Araucanía Norte | B6: Normalizacion Hospital Lonquimay (MOP) | C6: OBRA EXTRAORDINARIO Nº 57 | D6: ETAPA 3 FICHA N°44 REAS. | E6: AS/NTB | F6: Terminaciones | G6: 5564804 | H6: 0 | I6: 1044525 | J6: =+G6-H6+I6 -> 6609329 | K6: 0 | L6: 0 | M6: =+J6+L6 -> 6609329 | N6: 0rd. 79 del 17-01-23 | O6: 273 | P6: 44943 | Q6: 35239.79 | R6: =M6/Q6 -> 187.55302
A7: 22 Araucanía Sur | B7: NORMALIZACIÓN HOSPITAL COMUNITARIO Y FAMILIAR DR. EDUARDO GONZALEZ G, CUNCO | C7: 1.23 | D7: Instalaciones Domiciliarias afectadas | E7: AS/NTB | F7: Instalaciones/Sanitaria | G7: 0 | H7: 0 | I7: 0 | J7: =+G7-H7+I7 -> 0 | L7: 0 | M7: =+J7+L7 -> 0 | N7: ORD. N° 1823 del 29-05-17 | O7: C4/ 2192 del 28-06-17 | P7: 42884 | Q7: 26627.55 | R7: =M7/Q7 -> 0
A8: 22 Araucanía Sur | B8: NORMALIZACIÓN HOSPITAL COMUNITARIO Y FAMILIAR DR. EDUARDO GONZALEZ G, CUNCO | C8: 1.23.4 | D8: GLP | E8: AS/NTB | F8: Instalaciones/Climatización | G8: 0 | H8: 0 | I8: 0 | J8: =+G8-H8+I8 -> 0 | K8: 20 | L8: 0 | M8: =+J8+L8 -> 0 | N8: ORD. N° 1823 del 29-05-17 | O8: C4/ 2192 del 28-06-17 | P8: 42884 | Q8: 26627.55 | R8: =M8/Q8 -> 0
A9: 23 Araucanía Norte | B9: Normalizacion Hospital Lonquimay (MOP) | C9: OBRA EXTRAORDINARIO Nº 56 - FICHA 42 | D9: ETAPA 3 FICHA N°42 DENTAL. | E9: AS/NTB | F9: Terminaciones | G9: 15897894 | H9: 0 | I9: 3329307 | J9: =+G9-H9+I9 -> 19227201 | K9: 0 | L9: 0 | M9: =+J9+L9 -> 19227201 | N9: 0rd. 79 del 17-01-23 | O9: 273 | P9: 44943 | Q9: 35239.79 | R9: =M9/Q9 -> 545.61054
A10: 23 Araucanía Norte | B10: Normalizacion Hospital Lonquimay (MOP) | C10: OBRA EXTRAORDINARIO Nº 55 - FICHA 40 | D10: ETAPA 5 FICHA N°40 ESTERILIZACION. | E10: AS/NTB | F10: Terminaciones | G10: 1053313 | H10: 0 | I10: 883807 | J10: =+G10-H10+I10 -> 1937120 | K10: 0 | L10: 0 | M10: =+J10+L10 -> 1937120 | N10: 0rd. 79 del 17-01-23 | O10: 273 | P10: 44943 | Q10: 35239.79 | R10: =M10/Q10 -> 54.969681
A11: 23 Araucanía Norte | B11: Normalizacion Hospital Lonquimay (MOP) | C11: OBRA EXTRAORDINARIO Nº 54 - FICHA 39 | D11: ETAPA 5 FICHA N°39 ENTREGA CADAVERES. | E11: AS/NTB | F11: Terminaciones | G11: 1226081 | H11: 0 | I11: 294415 | J11: =+G11-H11+I11 -> 1520496 | K11: 0 | L11: 0 | M11: =+J11+L11 -> 1520496 | N11: 0rd. 79 del 17-01-23 | O11: 273 | P11: 44943 | Q11: 35239.79 | R11: =M11/Q11 -> 43.147136
A12: 23 Araucanía Norte | B12: Normalizacion Hospital Lonquimay (MOP) | C12: OBRA EXTRAORDINARIO Nº 53 | D12: ETAPA 5 FICHA N°38 GINECO-OBTETRICO. | E12: AS/NTB | F12: Terminaciones | G12: 0 | H12: 0 | I12: 12938405 | J12: =+G12-H12+I12 -> 12938405 | K12: 0 | L12: 0 | M12: =+J12+L12 -> 12938405 | N12: 0rd. 79 del 17-01-23 | O12: 273 | P12: 44943 | Q12: 35239.79 | R12: =M12/Q12 -> 367.15329
A13: 23 Araucanía Norte | B13: Normalizacion Hospital Lonquimay (MOP) | C13: OBRA EXTRAORDINARIO Nº 35 | D13: MODIFICACION REVESTIMIENTO DEL ACCESO DE AMBULANCIAS | E13: Errores de Diseño | F13: Terminaciones | G13: 614787 | H13: 0 | I13: 14139511 | J13: =+G13-H13+I13 -> 14754298 | K13: 0 | L13: 0 | M13: =+J13+L13 -> 14754298 | N13: 0rd. 79 del 17-01-23 | O13: 273 | P13: 44943 | Q13: 35239.79 | R13: =M13/Q13 -> 418.68291
A14: 23 Araucanía Norte | B14: Normalizacion Hospital Lonquimay (MOP) | C14: OBRA EXTRAORDINARIO Nº 27 | D14: MODIFICACION PARA ABASTECIMIENTO AGUA CALIENTE. | E14: Errores de Diseño | F14: Terminaciones | G14: 0 | H14: 1163368 | I14: 12264633 | J14: =+G14-H14+I14 -> 11101265 | K14: 0 | L14: 0 | M14: =+J14+L14 -> 11101265 | N14: 0rd. 79 del 17-01-23 | O14: 273 | P14: 44943 | Q14: 35239.79 | R14: =M14/Q14 -> 315.02075
A15: 23 Araucanía Norte | B15: Normalizacion Hospital Lonquimay (MOP) | C15: OBRA EXTRAORDINARIA TECNICA N°1 | D15: MURO DE CONTENCIÓN | E15: Funcionalidad | F15: Obra Gruesa | G15: 88136732 | H15: 3030990 | I15: 77526755 | J15: =+G15-H15+I15 -> 162632497 | K15: 0 | L15: 0 | M15: =+J15+L15 -> 162632497 | N15: Ord. 1297 del 12-09-22 | O15: 4036 | P15: 44816 | Q15: 34013.91 | R15: =M15/Q15 -> 4781.3526
A16: 23 Araucanía Norte | B16: Normalizacion Hospital Lonquimay (MOP) | C16: OBRA EXTRAORDINARIA Nº 8 | D16: Ficha N°13; Desplazamiento pasa muro en recinto C/1/33, Reubicar Instalación de lavado profundo, Reubicar enchufe computación doble y conexión telefoína y datos recinto C/1/33, Incluir puerta PM90, Redimensionamiento de tabique T1 y T2, Reubicar lavamanos 5, Se requiere redimensionar mueble MTCPC-300-800 para instalar autoclave proyectado e incorporar punto de datos en mesón de registro y entrega. | E16: AS/NTB | F16: Terminaciones | H16: 6132888 | J16: =+G16-H16+I16 -> -6132888 | K16: 0 | L16: 0 | M16: =+J16+L16 -> -6132888 | N16: Ord. 1589 del 08-10-21 | O16: 3997 | P16: 44477 | Q16: 30120.42 | R16: =M16/Q16 -> -203.6123
A17: 23 Araucanía Norte | B17: Normalizacion Hospital Lonquimay (MOP) | C17: OBRA EXTRAORDINARIA Nº 7 | D17: Ficha N°12; Incorporación de mica entre trabajo sucio y limpio, Incorporación de lavado profundo acero inox. De una cubeta, e instalaciones respectivas a estos artefactos. | E17: AS/NTB | F17: Terminaciones | J17: =+G17-H17+I17 -> 0 | K17: 0 | L17: 0 | M17: =+J17+L17 -> 0 | N17: Ord. 1589 del 08-10-21 | O17: 3997 | P17: 44477 | Q17: 30120.42 | R17: =M17/Q17 -> 0
A18: 23 Araucanía Norte | B18: Normalizacion Hospital Lonquimay (MOP) | C18: OBRA EXTRAORDINARIA Nº 68 | D18: ETAPA 3 FICHA N°43 EXTRACTORES. | E18: AS/NTB | F18: Terminaciones | G18: 2906579 | H18: 0 | I18: 4518987 | J18: =+G18-H18+I18 -> 7425566 | K18: 0 | L18: 0 | M18: =+J18+L18 -> 7425566 | N18: 0rd. 79 del 17-01-23 | O18: 273 | P18: 44943 | Q18: 35239.79 | R18: =M18/Q18 -> 210.71539
A19: 23 Araucanía Norte | B19: Normalizacion Hospital Lonquimay (MOP) | C19: OBRA EXTRAORDINARIA Nº 67 | D19: ETAPA 3 FICHA N°45 LABORATORIO BODEGA DE REACTIVOS C-128 | E19: AS/NTB | F19: Terminaciones | G19: 0 | H19: 0 | I19: 23510205 | J19: =+G19-H19+I19 -> 23510205 | K19: 0 | L19: 0 | M19: =+J19+L19 -> 23510205 | N19: 0rd. 79 del 17-01-23 | O19: 273 | P19: 44943 | Q19: 35239.79 | R19: =M19/Q19 -> 667.14941
A20: 23 Araucanía Norte | B20: Normalizacion Hospital Lonquimay (MOP) | C20: OBRA EXTRAORDINARIA Nº 66 | D20: ETAPA 5 FICHA N°17 DOSIS UNITARIA/BODEGA ACTIVA. | E20: AS/NTB | F20: Terminaciones | G20: 2819198 | H20: 0 | I20: 2407344 | J20: =+G20-H20+I20 -> 5226542 | K20: 0 | L20: 0 | M20: =+J20+L20 -> 5226542 | N20: 0rd. 79 del 17-01-23 | O20: 273 | P20: 44943 | Q20: 35239.79 | R20: =M20/Q20 -> 148.31365
A21: 23 Araucanía Norte | B21: Normalizacion Hospital Lonquimay (MOP) | C21: OBRA EXTRAORDINARIA Nº 65 | D21: ETAPA 3 FICHA N°41 RAYOS. | E21: AS/NTB | F21: Terminaciones | G21: 8103146 | H21: 0 | I21: 8032405 | J21: =+G21-H21+I21 -> 16135551 | K21: 0 | L21: 0 | M21: =+J21+L21 -> 16135551 | N21: 0rd. 79 del 17-01-23 | O21: 273 | P21: 44943 | Q21: 35239.79 | R21: =M21/Q21 -> 457.87875
A22: 23 Araucanía Norte | B22: Normalizacion Hospital Lonquimay (MOP) | C22: OBRA EXTRAORDINARIA Nº 64 | D22: ETAPA 5 FICHA N°37 URGENCIAS. | E22: AS/NTB | F22: Terminaciones | G22: 6478542 | H22: 0 | I22: 5841408 | J22: =+G22-H22+I22 -> 12319950 | K22: 0 | L22: 0 | M22: =+J22+L22 -> 12319950 | N22: 0rd. 79 del 17-01-23 | O22: 273 | P22: 44943 | Q22: 35239.79 | R22: =M22/Q22 -> 349.60339
A23: 23 Araucanía Norte | B23: Normalizacion Hospital Lonquimay (MOP) | C23: OBRA EXTRAORDINARIA Nº 62 | D23: ETAPA 3 FICHA N°18 PUERTA CENTRAL DE ALIMENTACION. | E23: AS/NTB | F23: Terminaciones | G23: 2183621 | H23: 0 | I23: 553662 | J23: =+G23-H23+I23 -> 2737283 | K23: 0 | L23: 0 | M23: =+J23+L23 -> 2737283 | N23: 0rd. 79 del 17-01-23 | O23: 273 | P23: 44943 | Q23: 35239.79 | R23: =M23/Q23 -> 77.675917
A24: 23 Araucanía Norte | B24: Normalizacion Hospital Lonquimay (MOP) | C24: OBRA EXTRAORDINARIA Nº 61 | D24: ETAPA 5 FICHA N°14 SEDILE. | E24: AS/NTB | F24: Terminaciones | G24: 3866375 | H24: 0 | I24: 2951680 | J24: =+G24-H24+I24 -> 6818055 | K24: 0 | L24: 0 | M24: =+J24+L24 -> 6818055 | N24: 0rd. 79 del 17-01-23 | O24: 273 | P24: 44943 | Q24: 35239.79 | R24: =M24/Q24 -> 193.47604
A25: 23 Araucanía Norte | B25: Normalizacion Hospital Lonquimay (MOP) | C25: OBRA EXTRAORDINARIA Nº 6 | D25: Ficha N°10 se requieren las siguientes modificaciones, en Recinto Rx se incluye señalética de advertencia RC universal | E25: AS/NTB | F25: Terminaciones | J25: =+G25-H25+I25 -> 0 | K25: 0 | L25: 0 | M25: =+J25+L25 -> 0 | N25: Ord. 1589 del 08-10-21 | O25: 3997 | P25: 44477 | Q25: 30120.42 | R25: =M25/Q25 -> 0
A26: 23 Araucanía Norte | B26: Normalizacion Hospital Lonquimay (MOP) | C26: OBRA EXTRAORDINARIA Nº 56 - FICHA 8 | D26: ETAPA 3 FICHA N°8 LAVANDERIA. | E26: AS/NTB | F26: Terminaciones | G26: 132773 | H26: 0 | I26: 1287549 | J26: =+G26-H26+I26 -> 1420322 | K26: 0 | L26: 0 | M26: =+J26+L26 -> 1420322 | N26: 0rd. 79 del 17-01-23 | O26: 273 | P26: 44943 | Q26: 35239.79 | R26: =M26/Q26 -> 40.304497
A27: 23 Araucanía Norte | B27: Normalizacion Hospital Lonquimay (MOP) | C27: OBRA EXTRAORDINARIA Nº 55 - FICHA 7 | D27: ETAPA 3 FICHA N°7 ESTERILIZACION. | E27: AS/NTB | F27: Terminaciones | G27: 10684208 | H27: 0 | I27: 12731434 | J27: =+G27-H27+I27 -> 23415642 | K27: 0 | L27: 0 | M27: =+J27+L27 -> 23415642 | N27: 0rd. 79 del 17-01-23 | O27: 273 | P27: 44943 | Q27: 35239.79 | R27: =M27/Q27 -> 664.46599
A28: 23 Araucanía Norte | B28: Normalizacion Hospital Lonquimay (MOP) | C28: OBRA EXTRAORDINARIA Nº 54 - FICHA 3 | D28: ETAPA 3 FICHA N°3 ENCHUFES PARA CATRES CLINICOS. | E28: AS/NTB | F28: Instalaciones/Eléctricas | G28: 0 | H28: 0 | I28: 1753112 | J28: =+G28-H28+I28 -> 1753112 | K28: 0 | L28: 0 | M28: =+J28+L28 -> 1753112 | N28: 0rd. 79 del 17-01-23 | O28: 273 | P28: 44943 | Q28: 35239.79 | R28: =M28/Q28 -> 49.748083
A29: 23 Araucanía Norte | B29: Normalizacion Hospital Lonquimay (MOP) | C29: OBRA EXTRAORDINARIA Nº 5 | D29: Ficha N°9; Eliminación artefactos de trabajo sucio N°18 logrando área para camilla. Reemplazo de WC infantil con estanque por WC universal con descarga a piso con flujómetro oculto y reubicar, reemplazar lavamanos mural para nicños por lavamanos universal y reubicación, reubicación de puerta y mudador, desplazar tabique T1 para permitir accesibilidad universal en baño, reemplazar tabiques por cortinas clínicas, reubicar lavamanos de uso clínico con semipedestal en el interior de área disiatría. | E29: AS/NTB | F29: Terminaciones | H29: 2507993 | J29: =+G29-H29+I29 -> -2507993 | K29: 0 | L29: 0 | M29: =+J29+L29 -> -2507993 | N29: Ord. 1589 del 08-10-21 | O29: 3997 | P29: 44477 | Q29: 30120.42 | R29: =M29/Q29 -> -83.265539
A30: 23 Araucanía Norte | B30: Normalizacion Hospital Lonquimay (MOP) | C30: OBRA EXTRAORDINARIA Nº 45 | D30: ETAPA 3, PUNTOS DE DATOS. | E30: AS/NTB | F30: Instalaciones/Eléctricas | G30: 10886540 | H30: 0 | I30: 7815153 | J30: =+G30-H30+I30 -> 18701693 | K30: 0 | L30: 0 | M30: =+J30+L30 -> 18701693 | N30: 0rd. 79 del 17-01-23 | O30: 273 | P30: 44943 | Q30: 35239.79 | R30: =M30/Q30 -> 530.6982
A31: 23 Araucanía Norte | B31: Normalizacion Hospital Lonquimay (MOP) | C31: OBRA EXTRAORDINARIA Nº 4 | D31: Ficha N°7; Modifica recintos de atención como abrrera sanitaria entre trbajo sucio y limpio, desplazamiento de enchufe computación doble hacia mueble de registro. Se requiere incorporar preinstalaciones de enchufe refuerzo de soporte , etc, para negatoscopio. Incorporación de enchufse de alumbrado doble, enchufe de computación y desplazar el módulo de punto de registro hacia el eje B. Se requiere desplazar enchufe de computación doble, enchufe de alumbrado doble y punto de datos hacia muro eje B. | E31: AS/NTB | F31: Terminaciones | J31: =+G31-H31+I31 -> 0 | K31: 0 | L31: 0 | M31: =+J31+L31 -> 0 | N31: Ord. 1589 del 08-10-21 | O31: 3997 | P31: 44477 | Q31: 30120.42 | R31: =M31/Q31 -> 0
A32: 23 Araucanía Norte | B32: Normalizacion Hospital Lonquimay (MOP) | C32: OBRA EXTRAORDINARIA Nº 3 | D32: Ficha N°6; Incorporación de lavadero mural mural botaguas de aseo, en recinto lavachatas, modificar la ubicación de gabinete colgante con puertas opacas, incluir 2 repisas mural por chata, incluir mica separadora como barrera sanitaria entre trabajo sucio y limpio. | E32: AS/NTB | F32: Terminaciones | H32: 414209 | J32: =+G32-H32+I32 -> -414209 | K32: 0 | L32: 0 | M32: =+J32+L32 -> -414209 | N32: Ord. 1589 del 08-10-21 | O32: 3997 | P32: 44477 | Q32: 30120.42 | R32: =M32/Q32 -> -13.751767
A33: 23 Araucanía Norte | B33: Normalizacion Hospital Lonquimay (MOP) | C33: OBRA EXTRAORDINARIA Nº 2 | D33: Ficha N°4; Configuración de un baño, incorporación de un lavadero mural para botaguas de aseo, incluir repisas murales para chata e incorporar mudador vertical. | E33: AS/NTB | F33: Terminaciones | H33: 5022846 | J33: =+G33-H33+I33 -> -5022846 | K33: 0 | L33: 0 | M33: =+J33+L33 -> -5022846 | N33: Ord. 1589 del 08-10-21 | O33: 3997 | P33: 44477 | Q33: 30120.42 | R33: =M33/Q33 -> -166.75883
A34: 23 Araucanía Norte | B34: Normalizacion Hospital Lonquimay (MOP) | C34: OBRA EXTRAORDINARIA Nº 1 | D34: Ficha N°3; Instalación de mallas mosquiteras en comedor, instalación de enchufe para nuevo refrigerador, reubicación de otro enchufe y aumento de cabida eléctrica de protección eléctrica. | E34: AS/NTB | F34: Terminaciones | J34: =+G34-H34+I34 -> 0 | K34: 0 | L34: 0 | M34: =+J34+L34 -> 0 | N34: Ord. 1589 del 08-10-21 | O34: 3997 | P34: 44477 | Q34: 30120.42 | R34: =M34/Q34 -> 0
A35: 23 Araucanía Norte | B35: Normalizacion Hospital Lonquimay (MOP) | C35: OBRA EXTRAORDINARIA N°52 | D35: PRVACIDAD Y PROTECCION SOLAR VENTANAS | E35: AS/NTB | F35: Terminaciones | G35: 18548019 | H35: 0 | I35: 7716281 | J35: =+G35-H35+I35 -> 26264300 | K35: 0 | L35: 0 | M35: =+J35+L35 -> 26264300 | N35: Ord. 1297 del 12-09-22 | O35: 4036 | P35: 44816 | Q35: 34013.91 | R35: =M35/Q35 -> 772.16351
A36: 23 Araucanía Norte | B36: Normalizacion Hospital Lonquimay (MOP) | C36: OBRA EXTRAORDINARIA N°51 | D36: FICHA N°51 SALA CUNA | E36: AS/NTB | F36: Terminaciones | G36: 1497479 | H36: 186851 | I36: 321043 | J36: =+G36-H36+I36 -> 1631671 | K36: 0 | L36: 0 | M36: =+J36+L36 -> 1631671 | N36: Ord. 1297 del 12-09-22 | O36: 4036 | P36: 44816 | Q36: 34013.91 | R36: =M36/Q36 -> 47.970698
A37: 23 Araucanía Norte | B37: Normalizacion Hospital Lonquimay (MOP) | C37: OBRA EXTRAORDINARIA N°50 | D37: FICHA N°36 CIRUGIA MENOR | E37: AS/NTB | F37: Terminaciones | G37: 2319796 | H37: 0 | I37: 0 | J37: =+G37-H37+I37 -> 2319796 | K37: 0 | L37: 0 | M37: =+J37+L37 -> 2319796 | N37: Ord. 1297 del 12-09-22 | O37: 4036 | P37: 44816 | Q37: 34013.91 | R37: =M37/Q37 -> 68.201392
A38: 23 Araucanía Norte | B38: Normalizacion Hospital Lonquimay (MOP) | C38: OBRA EXTRAORDINARIA N°49 | D38: FICHA N°35 REAS | E38: AS/NTB | F38: Terminaciones | G38: 2557957 | H38: 0 | I38: 1963755 | J38: =+G38-H38+I38 -> 4521712 | K38: 0 | L38: 0 | M38: =+J38+L38 -> 4521712 | N38: Ord. 1297 del 12-09-22 | O38: 4036 | P38: 44816 | Q38: 34013.91 | R38: =M38/Q38 -> 132.93714
A39: 23 Araucanía Norte | B39: Normalizacion Hospital Lonquimay (MOP) | C39: OBRA EXTRAORDINARIA N°48 | D39: FICHA N°34 SEDILE | E39: AS/NTB | F39: Terminaciones | G39: 2736783 | H39: 0 | I39: 1312186 | J39: =+G39-H39+I39 -> 4048969 | K39: 0 | L39: 0 | M39: =+J39+L39 -> 4048969 | N39: Ord. 1297 del 12-09-22 | O39: 4036 | P39: 44816 | Q39: 34013.91 | R39: =M39/Q39 -> 119.03862
A40: 23 Araucanía Norte | B40: Normalizacion Hospital Lonquimay (MOP) | C40: OBRA EXTRAORDINARIA N°47 | D40: FICHA N°33 ALIMENTACION | E40: AS/NTB | F40: Terminaciones | G40: 0 | H40: 0 | I40: 746610 | J40: =+G40-H40+I40 -> 746610 | K40: 0 | L40: 0 | M40: =+J40+L40 -> 746610 | N40: Ord. 1297 del 12-09-22 | O40: 4036 | P40: 44816 | Q40: 34013.91 | R40: =M40/Q40 -> 21.950137
A41: 23 Araucanía Norte | B41: Normalizacion Hospital Lonquimay (MOP) | C41: OBRA EXTRAORDINARIA N°46 | D41: FICHA N°32 ESTERILIZACION | E41: AS/NTB | F41: Terminaciones | G41: 1275754 | H41: 5412841 | I41: 3460944 | J41: =+G41-H41+I41 -> -676143 | K41: 0 | L41: 0 | M41: =+J41+L41 -> -676143 | N41: Ord. 1297 del 12-09-22 | O41: 4036 | P41: 44816 | Q41: 34013.91 | R41: =M41/Q41 -> -19.878426
A42: 23 Araucanía Norte | B42: Normalizacion Hospital Lonquimay (MOP) | C42: OBRA EXTRAORDINARIA N°45 | D42: FICHA 31 ALIMANTACION | E42: AS/NTB | F42: Terminaciones | G42: 2038413 | H42: 0 | I42: 7158625 | J42: =+G42-H42+I42 -> 9197038 | K42: 0 | L42: 0 | M42: =+J42+L42 -> 9197038 | N42: Ord. 1297 del 12-09-22 | O42: 4036 | P42: 44816 | Q42: 34013.91 | R42: =M42/Q42 -> 270.3905
A43: 23 Araucanía Norte | B43: Normalizacion Hospital Lonquimay (MOP) | C43: OBRA EXTRAORDINARIA N°44 | D43: FICHA N°17 FARMACIA | E43: AS/NTB | F43: Terminaciones | G43: 1779973 | H43: 0 | I43: 12543754 | J43: =+G43-H43+I43 -> 14323727 | K43: 0 | L43: 0 | M43: =+J43+L43 -> 14323727 | N43: Ord. 1297 del 12-09-22 | O43: 4036 | P43: 44816 | Q43: 34013.91 | R43: =M43/Q43 -> 421.1138
A44: 23 Araucanía Norte | B44: Normalizacion Hospital Lonquimay (MOP) | C44: OBRA EXTRAORDINARIA N°43 | D44: FICHA N°30 BODEGA PNAC Y FARM. | E44: AS/NTB | F44: Terminaciones | G44: 6153112 | H44: 0 | I44: 43855529 | J44: =+G44-H44+I44 -> 50008641 | K44: 0 | L44: 0 | M44: =+J44+L44 -> 50008641 | N44: Ord. 1297 del 12-09-22 | O44: 4036 | P44: 44816 | Q44: 34013.91 | R44: =M44/Q44 -> 1470.2409
A45: 23 Araucanía Norte | B45: Normalizacion Hospital Lonquimay (MOP) | C45: OBRA EXTRAORDINARIA N°42 | D45: FICHA N°29 MALLAS MOSQUITERAS | E45: AS/NTB | F45: Terminaciones | G45: 0 | H45: 0 | I45: 2862487 | J45: =+G45-H45+I45 -> 2862487 | K45: 0 | L45: 0 | M45: =+J45+L45 -> 2862487 | N45: Ord. 1297 del 12-09-22 | O45: 4036 | P45: 44816 | Q45: 34013.91 | R45: =M45/Q45 -> 84.156364
A46: 23 Araucanía Norte | B46: Normalizacion Hospital Lonquimay (MOP) | C46: OBRA EXTRAORDINARIA N°41 | D46: FICHA N°27 MUEBLES ACC 6 | E46: AS/NTB | F46: Terminaciones | G46: 938215 | H46: 6405262 | I46: 8325958 | J46: =+G46-H46+I46 -> 2858911 | K46: 0 | L46: 0 | M46: =+J46+L46 -> 2858911 | N46: Ord. 1297 del 12-09-22 | O46: 4036 | P46: 44816 | Q46: 34013.91 | R46: =M46/Q46 -> 84.051231
... A60: 23 Araucanía Norte | B60: Normalizacion Hospital Lonquimay (MOP) | C60: OBRA EXTRAORDINARIA N°23 | D60: FICHA N°4 TOMA DE MUESTRAS | E60: AS/NTB | F60: Instalaciones/Eléctricas | G60: 970897 | H60: 0 | I60: 0 | J60: =+G60-H60+I60 -> 970897 | K60: 0 | L60: 0 | M60: =+J60+L60 -> 970897 | N60: Ord. 1297 del 12-09-22 | O60: 4036 | P60: 44816 | Q60: 34013.91 | R60: =M60/Q60 -> 28.544116
A61: 12 Metropolitano Occidente | B61: Reposición con Relocalización Hospital de Melipilla | C61: 2.22 | D61: Modificación de refuerzos de tabiqueria para alojar puertas, tabiques vidriados y ventanas de fachada | E61: Errores de Diseño | F61: Obra Gruesa | G61: 0 | H61: 4739963 | I61: 0 | J61: =+G61-H61+I61 -> -4739963 | L61: 0 | M61: =+J61+L61 -> -4739963 | N61: ORD. 0713 | O61: Ord C4/2669 del 01-09-2021 | P61: 44341 | Q61: 29513.76 | R61: -161
A62: 23 Araucanía Norte | B62: Normalizacion Hospital Lonquimay (MOP) | C62: OBRA EXTRAORDINARIA N°21 | D62: FICHA N°2 ENCHUFES EDIFICIO B | E62: AS/NTB | F62: Instalaciones/Eléctricas | G62: 2951420 | H62: 0 | I62: 110527 | J62: =+G62-H62+I62 -> 3061947 | K62: 0 | L62: 0 | M62: =+J62+L62 -> 3061947 | N62: Ord. 1297 del 12-09-22 | O62: 4036 | P62: 44816 | Q62: 34013.91 | R62: =M62/Q62 -> 90.020436
A63: 23 Araucanía Norte | B63: Normalizacion Hospital Lonquimay (MOP) | C63: OBRA EXTRAORDINARIA N°20 | D63: FICHA N°1 EQUIPOS MEDICOS | E63: AS/NTB | F63: Instalaciones/Eléctricas | G63: 5717419 | H63: 0 | I63: 331582 | J63: =+G63-H63+I63 -> 6049001 | K63: 0 | L63: 0 | M63: =+J63+L63 -> 6049001 | N63: Ord. 1297 del 12-09-22 | O63: 4036 | P63: 44816 | Q63: 34013.91 | R63: =M63/Q63 -> 177.83904
A64: 23 Araucanía Norte | B64: Normalizacion Hospital Lonquimay (MOP) | C64: OBRA EXTRAORDINARIA N°19 | D64: Ficha N°18; Incorporar rejilla de desagüe en xona de acceso. | E64: AS/NTB | F64: Terminaciones | I64: 16977422 | J64: =+G64-H64+I64 -> 16977422 | K64: 0 | L64: 0 | M64: =+J64+L64 -> 16977422 | N64: Ord. 109 del 02-02-22 | O64: 774 | P64: 44594 | Q64: 31228.7 | R64: =M64/Q64 -> 543.64805
A65: 23 Araucanía Norte | B65: Normalizacion Hospital Lonquimay (MOP) | C65: OBRA EXTRAORDINARIA N°18 | D65: Ficha N°19; Habilitar baño acc. Universal, incluir; casilleros y lavamanos, Reemplazar WC infatil con estanque por WC con descarga a piso con fluxómetro expuesto. Mallas mosquiteras. | E65: AS/NTB | F65: Terminaciones | H65: 3217274 | J65: =+G65-H65+I65 -> -3217274 | K65: 0 | L65: 0 | M65: =+J65+L65 -> -3217274 | N65: Ord. 109 del 02-02-22 | O65: 774 | P65: 44594 | Q65: 31228.7 | R65: =M65/Q65 -> -103.02299
A66: 23 Araucanía Norte | B66: Normalizacion Hospital Lonquimay (MOP) | C66: OBRA EXTRAORDINARIA Nº 44 | D66: PREINSTALACIONES ELECTRICAS ANTENA. | E66: AS/NTB | F66: Instalaciones/Eléctricas | G66: 10676615 | H66: 0 | I66: 16926402 | J66: =+G66-H66+I66 -> 27603017 | K66: 0 | L66: 0 | M66: =+J66+L66 -> 27603017 | N66: 0rd. 79 del 17-01-23 | O66: 273 | P66: 44943 | Q66: 35239.79 | R66: =M66/Q66 -> 783.29119
A67: 04 Atacama | B67: Hospital Comunitario Diego de Almagro | C67: 11 | D67: Rack de Comunicaciones | E67: Funcionalidad | F67: Instalaciones/Corrientes Débiles | G67: 0 | H67: 6693750 | I67: 0 | J67: =+G67-H67+I67 -> -6693750 | L67: 0 | M67: =+J67+L67 -> -6693750 | N67: ORD.2543 | O67: ORD.533 | P67: 44166 | Q67: 29036.92 | R67: =M67/Q67 -> -230.52548
A68: 08 Valparaíso San Antonio | B68: Normalización Hospital Claudio Vicuña, San Antonio | C68: Nota de Cambio N°99 | D68: Nuevo antepecho en Recinto Área Entrega de Bandejas | E68: Errores de Diseño | F68: Terminaciones | G68: 934082 | I68: 52907 | J68: =+G68-H68+I68 -> 986989 | K68: 0 | L68: 0 | M68: =+J68+L68 -> 986989 | N68: Ord.N°1412 del 13.08.21 | O68: ORD. 2728 | P68: 44383 | Q68: 29981.28 | R68: =M68/Q68 -> 32.920176
A69: 22 Araucanía Sur | B69: Normalizacion Hospital Villarrica | C69: Nota de Cambio N°98 | D69: Modificación puertas en vías de evacuación | E69: Normativa (OGUC, Serviu, etc.) | F69: Terminaciones | G69: 1265459 | H69: 0 | I69: 4419337 | J69: =+G69-H69+I69 -> 5684796 | K69: 0 | L69: 0 | M69: =+J69+L69 -> 5684796 | N69: Ord. 0016 del 06-01-2023 SSAS | O69: ORD. 1062 | P69: 44932 | Q69: 35178.67 | R69: =M69/Q69 -> 161.59781
A70: 08 Valparaíso San Antonio | B70: Normalización Hospital Claudio Vicuña, San Antonio | C70: Nota de Cambio N°97 rev2 | D70: Nuevos requerimientos UPS | E70: Errores de Diseño | F70: Instalaciones/Eléctricas | G70: 0 | H70: 0 | I70: 23914172 | J70: =+G70-H70+I70 -> 23914172 | K70: 0 | L70: 0 | M70: =+J70+L70 -> 23914172 | N70: Ord.N°935 del 19.05.21 | O70: ORD. 1666 | P70: 44335 | Q70: 29567.53 | R70: =M70/Q70 -> 808.79844
A71: 22 Araucanía Sur | B71: Normalizacion Hospital Villarrica | C71: Nota de Cambio N°97 | D71: Modificación puertas vestidores Imagenología y cirugía menor | E71: Normativa (OGUC, Serviu, etc.) | F71: Terminaciones | G71: 371477 | H71: 0 | I71: 8623736 | J71: =+G71-H71+I71 -> 8995213 | K71: 0 | L71: 0 | M71: =+J71+L71 -> 8995213 | N71: Ord. 0016 del 06-01-2023 SSAS | O71: ORD. 1062 | P71: 44932 | Q71: 35178.67 | R71: =M71/Q71 -> 255.70077
A72: 08 Valparaíso San Antonio | B72: Normalización Hospital Claudio Vicuña, San Antonio | C72: Nota de Cambio N°96 rev2 | D72: aumento estructura metálica escalera para instalación de fachada | E72: Errores de Diseño | F72: Obra Gruesa | G72: 8317617 | H72: 0 | I72: 765500 | J72: =+G72-H72+I72 -> 9083117 | K72: 0 | L72: 0 | M72: =+J72+L72 -> 9083117 | N72: Ord.N°935 del 19.05.21 | O72: ORD. 1666 | P72: 44335 | Q72: 29567.53 | R72: =M72/Q72 -> 307.19905
A73: 22 Araucanía Sur | B73: Normalizacion Hospital Villarrica | C73: Nota de Cambio N°96 | D73: Zócalo contenedor de derrame en grupos generadores | E73: Errores de Diseño | F73: Terminaciones | G73: 0 | H73: 0 | I73: 3026383 | J73: =+G73-H73+I73 -> 3026383 | K73: 0 | L73: 0 | M73: =+J73+L73 -> 3026383 | N73: Ord. 0016 del 06-01-2023 SSAS | O73: ORD. 1062 | P73: 44932 | Q73: 35178.67 | R73: =M73/Q73 -> 86.02892
A74: 08 Valparaíso San Antonio | B74: Normalización Hospital Claudio Vicuña, San Antonio | C74: Nota de Cambio N°94 rev2 | D74: modificación columna de gases clinicos | E74: Errores de Diseño | F74: Instalaciones/Gases Clínicos | G74: 12037834 | H74: 416300053 | I74: 752621431 | J74: =+G74-H74+I74 -> 348359212 | K74: 0 | L74: 0 | M74: =+J74+L74 -> 348359212 | N74: Ord.N°935 del 19.05.21 | O74: ORD. 1666 | P74: 44335 | Q74: 29567.53 | R74: =M74/Q74 -> 11781.816
A75: 08 Valparaíso San Antonio | B75: Normalización Hospital Claudio Vicuña, San Antonio | C75: Nota de Cambio N°93 rev2 | D75: nuevo refuerzo sala generadores | E75: Errores de Diseño | F75: Obra Gruesa | G75: 6501346 | H75: 0 | I75: 5411358 | J75: =+G75-H75+I75 -> 11912704 | K75: 0 | L75: 0 | M75: =+J75+L75 -> 11912704 | N75: Ord.N°935 del 19.05.21 | O75: ORD. 1666 | P75: 44335 | Q75: 29567.53 | R75: =M75/Q75 -> 402.89818
A76: 08 Valparaíso San Antonio | B76: Normalización Hospital Claudio Vicuña, San Antonio | C76: Nota de Cambio N°92 | D76: Modificación ventanas cafeteria piso 3 | E76: Errores de Diseño | F76: Terminaciones | G76: 6113445 | H76: 3785796 | J76: =+G76-H76+I76 -> 2327649 | K76: 0 | L76: 0 | M76: =+J76+L76 -> 2327649 | N76: Ord.N°1915 del 04.11.21 | O76: ORD. 3830 | P76: 44531 | Q76: 30776.05 | R76: =M76/Q76 -> 75.631831
A77: 22 Araucanía Sur | B77: Normalizacion Hospital Villarrica | C77: Nota de Cambio N°92 | D77: Modificación puertas laboratorio | E77: Errores de Diseño | F77: Terminaciones | G77: 0 | H77: 0 | I77: 1057498 | J77: =+G77-H77+I77 -> 1057498 | K77: 0 | L77: 0 | M77: =+J77+L77 -> 1057498 | N77: Ord. 0016 del 06-01-2023 SSAS | O77: ORD. 1062 | P77: 44932 | Q77: 35178.67 | R77: =M77/Q77 -> 30.060773
A78: 08 Valparaíso San Antonio | B78: Normalización Hospital Claudio Vicuña, San Antonio | C78: Nota de Cambio N°91 rev3 | D78: Modificación estructura metálica perimetral helipuerto | E78: Errores de Diseño | F78: Obra Gruesa | G78: 30937422 | H78: 13200052 | I78: 26085452 | J78: =+G78-H78+I78 -> 43822822 | K78: 0 | L78: 0 | M78: =+J78+L78 -> 43822822 | N78: Ord.N°0432 del 10.03.21 | O78: ORD. 1324 | P78: 44265 | Q78: 29355.01 | R78: =M78/Q78 -> 1492.8567
A79: 08 Valparaíso San Antonio | B79: Normalización Hospital San Jose, Casablanca | C79: Nota de Cambio N°91 | D79: Definición de estructura metálica accesos exteriores rdi 173 | E79: Errores de Diseño | F79: Terminaciones | G79: 0 | H79: 18065315 | I79: 19640712 | J79: =+G79-H79+I79 -> 1575397 | K79: 0 | L79: 0 | M79: =+J79+L79 -> 1575397 | N79: ORD. 518 del 25.03.21 | O79: ORD.1123 | P79: 44280 | Q79: 29383.41 | R79: =M79/Q79 -> 53.615186
A80: 08 Valparaíso San Antonio | B80: Normalización Hospital San Jose, Casablanca | C80: Nota de Cambio N°90 Rev.2 | D80: Aumento capacidad de generador, transformador y banco de condensadores | E80: Errores de Diseño | F80: Instalaciones/Eléctricas | G80: 4499341 | H80: 69169464 | I80: 74756573 | J80: =+G80-H80+I80 -> 10086450 | K80: 0 | L80: 0 | M80: =+J80+L80 -> 10086450 | N80: ORD. 0360 del 23.02.2021 | O80: ORD. 675 | P80: 44250 | Q80: 29250.92 | R80: =M80/Q80 -> 344.82505
A81: 22 Araucanía Sur | B81: Normalizacion Hospital Villarrica | C81: Nota de Cambio N°90 | D81: Muretes de contención sector eje 17 | E81: Errores de Diseño | F81: Obra Gruesa | G81: 3075451 | H81: 0 | I81: 269892 | J81: =+G81-H81+I81 -> 3345343 | K81: 0 | L81: 0 | M81: =+J81+L81 -> 3345343 | N81: Ord. 0016 del 06-01-2023 SSAS | O81: ORD. 1062 | P81: 44932 | Q81: 35178.67 | R81: =M81/Q81 -> 95.095778
A82: 17 Ñuble | B82: Construcción Nuevo Complejo Hospitalario Provincia de Ñuble | C82: Nota de Cambio N°9 | D82: Modificación Cerco C3 | E82: Errores de Diseño | F82: Obras Previas | G82: 0 | H82: 0 | I82: 4084790 | J82: =+G82-H82+I82 -> 4084790 | K82: 0 | L82: 0 | M82: =+J82+L82 -> 4084790 | N82: ORD 370 SSÑ del 08.04.21 | O82: ORD. 1328 | P82: 44294 | Q82: 29409.93 | R82: =M82/Q82 -> 138.89152
A83: 08 Valparaíso San Antonio | B83: Normalización Hospital San Jose, Casablanca | C83: Nota de Cambio N°9 | D83: Calculo estructura EJE 28a RDI n°68 | E83: Errores de Diseño | F83: Obra Gruesa | G83: 455170 | H83: 0 | I83: 0 | J83: =+G83-H83+I83 -> 455170 | K83: 0 | L83: 0 | M83: =+J83+L83 -> 455170 | N83: ORD. 935 del 11.06.20 | O83: C4 N° 2223 del 15-07-20 | P83: 43993 | Q83: 28714.6 | R83: =M83/Q83 -> 15.851518
A84: 08 Valparaíso San Antonio | B84: Normalización Hospital San Jose, Casablanca | C84: Nota de Cambio N°89 Rev. 1 | D84: Nota de Cambio Modificación central de alimentación | E84: Errores de Diseño | F84: Instalaciones/Eléctricas | G84: 0 | H84: 0 | I84: 3256181 | J84: =+G84-H84+I84 -> 3256181 | K84: 0 | L84: 0 | M84: =+J84+L84 -> 3256181 | N84: ORD. 0390 del 02.03.21 | O84: ORD. 945 | P84: 44257 | Q84: 29301.98 | R84: =M84/Q84 -> 111.12495
A85: 22 Araucanía Sur | B85: Normalizacion Hospital Villarrica | C85: Nota de Cambio N°89 | D85: Obras de accesibilidad universal sector jardín infantil | E85: Normativa (OGUC, Serviu, etc.) | F85: Terminaciones | G85: 0 | H85: 0 | I85: 14087916 | J85: =+G85-H85+I85 -> 14087916 | K85: 0 | L85: 0 | M85: =+J85+L85 -> 14087916 | N85: Ord. 0016 del 06-01-2023 SSAS | O85: ORD. 1062 | P85: 44932 | Q85: 35178.67 | R85: =M85/Q85 -> 400.46756
A86: 08 Valparaíso San Antonio | B86: Normalización Hospital Claudio Vicuña, San Antonio | C86: Nota de Cambio N°88 | D86: nueva estructura metálica data center | E86: Errores de Diseño | F86: Obra Gruesa | G86: 589261 | H86: 0 | I86: 28006740 | J86: =+G86-H86+I86 -> 28596001 | K86: 0 | L86: 0 | M86: =+J86+L86 -> 28596001 | N86: Ord.N°935 del 19.05.21 | O86: ORD. 1666 | P86: 44335 | Q86: 29567.53 | R86: =M86/Q86 -> 967.14203
A87: 22 Araucanía Sur | B87: Normalizacion Hospital Villarrica | C87: Nota de Cambio N°88 | D87: Incorporación señales de seguridad | E87: Funcionalidad | F87: Terminaciones | G87: 31545 | H87: 0 | I87: 8505188 | J87: =+G87-H87+I87 -> 8536733 | K87: 0 | L87: 0 | M87: =+J87+L87 -> 8536733 | N87: Ord. 0016 del 06-01-2023 SSAS | O87: ORD. 1062 | P87: 44932 | Q87: 35178.67 | R87: =M87/Q87 -> 242.66787
A88: 22 Araucanía Sur | B88: Normalizacion Hospital Villarrica | C88: Nota de Cambio N°87 | D88: Incorporación válvula ventosa en red extensión agua potable | E88: Funcionalidad | F88: Instalaciones/Sanitaria | G88: 0 | H88: 0 | I88: 5948870 | J88: =+G88-H88+I88 -> 5948870 | K88: 0 | L88: 0 | M88: =+J88+L88 -> 5948870 | N88: Ord. 0016 del 06-01-2023 SSAS | O88: ORD. 1062 | P88: 44932 | Q88: 35178.67 | R88: =M88/Q88 -> 169.10446
... A92: 22 Araucanía Sur | B92: Construcción Complejo Asistencial Padre Las Casas | C92: Nota de Cambio N°85 | D92: Obras solicitadas por Bomberos para recepción de las obras | E92: Funcionalidad | F92: Instalaciones/Seguridad | G92: 204753 | H92: 0 | I92: 18145197 | J92: =+G92-H92+I92 -> 18349950 | K92: 0 | L92: 0 | M92: =+J92+L92 -> 18349950 | N92: ORD. 0121 SSAR, 16-01-2020. | O92: ORD C4/0555 del 09-03-2020 | P92: 43846 | Q92: 28324.55 | R92: =M92/Q92 -> 647.84613
A93: 12 Metropolitano Occidente | B93: Reposición con Relocalización Hospital de Melipilla | C93: 3.02 | D93: Redución de superficie de aplicación de EIFS en las vigas de subterráneo | E93: Errores de Diseño | F93: Terminaciones | G93: 0 | H93: 18862867 | I93: 0 | J93: =+G93-H93+I93 -> -18862867 | L93: 0 | M93: =+J93+L93 -> -18862867 | N93: ORD. 0713 | O93: Ord C4/492 del 09-02-2022 | P93: 44341 | Q93: 29513.76 | R93: -639
A94: 22 Araucanía Sur | B94: Normalizacion Hospital Villarrica | C94: Nota de Cambio N°85 | D94: Plataforma metálica para muestreo isocinetico | E94: AS/NTB | F94: Terminaciones | G94: 1657279 | H94: 0 | I94: 9610672 | J94: =+G94-H94+I94 -> 11267951 | K94: 0 | L94: 0 | M94: =+J94+L94 -> 11267951 | N94: Ord. 0016 del 06-01-2023 SSAS | O94: ORD. 1062 | P94: 44932 | Q94: 35178.67 | R94: =M94/Q94 -> 320.30634
A95: 22 Araucanía Sur | B95: Construcción Complejo Asistencial Padre Las Casas | C95: Nota de Cambio N°84 | D95: Automatización cilindros agua caliente sanitaria para control legionela y control con sistema de colectores solares | E95: Errores de Diseño | F95: Instalaciones/Sanitaria | G95: 13002110 | H95: 0 | I95: 9154170 | J95: =+G95-H95+I95 -> 22156280 | K95: 0 | L95: 0 | M95: =+J95+L95 -> 22156280 | N95: ORD. 0121 SSAR, 16-01-2020. | O95: ORD C4/0555 del 09-03-2020 | P95: 43846 | Q95: 28324.55 | R95: =M95/Q95 -> 782.22884
A96: 08 Valparaíso San Antonio | B96: Normalización Hospital Claudio Vicuña, San Antonio | C96: Nota de Cambio N°84 | D96: Acero Estructural Escalera Acceso Patio Ambulancias | E96: Errores de Diseño | F96: Obra Gruesa | G96: 779130 | H96: 114803 | J96: =+G96-H96+I96 -> 664327 | K96: 0 | L96: 0 | M96: =+J96+L96 -> 664327 | N96: Ord.N°1412 del 13.08.21 | O96: ORD. 2728 | P96: 44383 | Q96: 29981.28 | R96: =M96/Q96 -> 22.15806
A97: 22 Araucanía Sur | B97: Normalizacion Hospital Villarrica | C97: Nota de Cambio N°84 | D97: Modificacion tabiques ascensores (1A Y 1B) | E97: Funcionalidad | F97: Terminaciones | G97: 0 | H97: 0 | I97: 20347868 | J97: =+G97-H97+I97 -> 20347868 | K97: 0 | L97: 0 | M97: =+J97+L97 -> 20347868 | N97: Ord. 0016 del 06-01-2023 SSAS | O97: ORD. 1062 | P97: 44932 | Q97: 35178.67 | R97: =M97/Q97 -> 578.41493
A98: 08 Valparaíso San Antonio | B98: Normalización Hospital Claudio Vicuña, San Antonio | C98: Nota de Cambio N°83 rev2 | D98: Ejecución de nuevas pilas sector gases clinicos | E98: Errores de Diseño | F98: Obra Gruesa | G98: 56893849 | H98: 0 | I98: 0 | J98: =+G98-H98+I98 -> 56893849 | K98: 0 | L98: 0 | M98: =+J98+L98 -> 56893849 | N98: Ord.N°0432 del 10.03.21 | O98: ORD. 1324 | P98: 44265 | Q98: 29355.01 | R98: =M98/Q98 -> 1938.1308
A99: 08 Valparaíso San Antonio | B99: Normalización Hospital San Jose, Casablanca | C99: Nota de Cambio N°83 Rev. 0 | D99: Arquitectura muro cortina ventanas V32 / V33 /V34 / V35 RDI 252 | E99: Errores de Diseño | F99: Terminaciones | G99: 57297935 | H99: 50033859 | I99: 0 | J99: =+G99-H99+I99 -> 7264076 | K99: 0 | L99: 0 | M99: =+J99+L99 -> 7264076 | N99: ORD. 0390 del 02.03.21 | O99: ORD. 945 | P99: 44257 | Q99: 29301.98 | R99: =M99/Q99 -> 247.90393
A100: 22 Araucanía Sur | B100: Construcción Complejo Asistencial Padre Las Casas | C100: Nota de Cambio N°83 | D100: Modificación eléctrica por equipos médicos | E100: Funcionalidad | F100: Instalaciones/Eléctricas | G100: 10630890 | H100: 32313029 | I100: 22306707 | J100: =+G100-H100+I100 -> 624568 | K100: 0 | L100: 0 | M100: =+J100+L100 -> 624568 | N100: ORD. 0121 SSAR, 16-01-2020. | O100: ORD C4/0555 del 09-03-2020 | P100: 43846 | Q100: 28324.55 | R100: =M100/Q100 -> 22.050412
A101: 22 Araucanía Sur | B101: Normalizacion Hospital Villarrica | C101: Nota de Cambio N°83 | D101: Reparación red agua potable exterior | E101: Normativa (OGUC, Serviu, etc.) | F101: Instalaciones/Sanitaria | G101: 0 | H101: 0 | I101: 44516856 | J101: =+G101-H101+I101 -> 44516856 | K101: 0 | L101: 0 | M101: =+J101+L101 -> 44516856 | N101: Ord. 0016 del 06-01-2023 SSAS | O101: ORD. 1062 | P101: 44932 | Q101: 35178.67 | R101: =M101/Q101 -> 1265.4502
A102: 08 Valparaíso San Antonio | B102: Normalización Hospital San Jose, Casablanca | C102: Nota de Cambio N°82 Rev. 3 | D102: Helipuerto RDI 36 FOI 238 | E102: Funcionalidad | F102: Terminaciones | G102: 0 | H102: 12230861 | I102: 0 | J102: =+G102-H102+I102 -> -12230861 | K102: 0 | L102: 0 | M102: =+J102+L102 -> -12230861 | N102: ORD. 0390 del 02.03.21 | O102: ORD. 945 | P102: 44257 | Q102: 29301.98 | R102: =M102/Q102 -> -417.40732
A103: 22 Araucanía Sur | B103: Construcción Complejo Asistencial Padre Las Casas | C103: Nota de Cambio N°82 | D103: Instalación de arranques de climatización, gases clínicos y agua potable para incorporación nuevas tecnologías | E103: Funcionalidad | F103: Instalaciones/Climatización | G103: 6034760 | H103: 0 | I103: 2081617 | J103: =+G103-H103+I103 -> 8116377 | K103: 0 | L103: 0 | M103: =+J103+L103 -> 8116377 | N103: ORD. 0121 SSAR, 16-01-2020. | O103: ORD C4/0555 del 09-03-2020 | P103: 43846 | Q103: 28324.55 | R103: =M103/Q103 -> 286.54919
A104: 22 Araucanía Sur | B104: Normalizacion Hospital Villarrica | C104: Nota de Cambio N°82 | D104: Ingenieria pasarela estero iribarren | E104: Errores de Diseño | F104: Terminaciones | G104: 0 | H104: 0 | I104: 2985006 | J104: =+G104-H104+I104 -> 2985006 | K104: 0 | L104: 0 | M104: =+J104+L104 -> 2985006 | N104: Ord. 0016 del 06-01-2023 SSAS | O104: ORD. 1062 | P104: 44932 | Q104: 35178.67 | R104: =M104/Q104 -> 84.852725
A105: 22 Araucanía Sur | B105: Normalizacion Hospital Villarrica | C105: Nota de Cambio N°81.18 | D105: Incremento baranda escalera 1 | E105: Errores de Diseño | F105: Terminaciones | I105: 35295876 | J105: =+G105-H105+I105 -> 35295876 | K105: 0 | L105: 0 | M105: =+J105+L105 -> 35295876 | N105: Ord. 1918 del 22.07.22 SSAS | O105: ORD. 2858 | P105: 44764 | Q105: 33330.45 | R105: =M105/Q105 -> 1058.9679
A106: 22 Araucanía Sur | B106: Normalizacion Hospital Villarrica | C106: Nota de Cambio N°81.17 | D106: Modificaciones jardín Infantil | E106: Funcionalidad | F106: Terminaciones | H106: 5929720 | I106: 11869996 | J106: =+G106-H106+I106 -> 5940276 | K106: 0 | L106: 0 | M106: =+J106+L106 -> 5940276 | N106: Ord. 1918 del 22.07.22 SSAS | O106: ORD. 2858 | P106: 44764 | Q106: 33330.45 | R106: =M106/Q106 -> 178.2237
A107: 19 Talcahuano | B107: Normalización 3°Etapa y Final Hospital Las Higueras, Talcahuano | C107: 580 | D107: Disminución no montaje ascensor N°8, edificio técnico | E107: Errores de Diseño | F107: TERMINACIONES | G107: 0 | H107: 30876467 | I107: 0 | J107: =+G107-H107+I107 -> -30876467 | K107: en revisión | L107: 0 | M107: =+J107+L107 -> -30876467 | N107: ORD. 1449 | O107: Ord C4/3050 del 31-08-2022 | P107: 44502 | Q107: 30403.92 | R107: =+M107/Q107 -> -1015.5423
A108: 22 Araucanía Sur | B108: Normalizacion Hospital Villarrica | C108: Nota de Cambio N°81.16 | D108: Ventilación cámaras desgrasadoras | E108: Funcionalidad | F108: Instalaciones/Climatización | G108: 1819693 | I108: 152189 | J108: =+G108-H108+I108 -> 1971882 | K108: 0 | L108: 0 | M108: =+J108+L108 -> 1971882 | N108: Ord. 1918 del 22.07.22 SSAS | O108: ORD. 2858 | P108: 44764 | Q108: 33330.45 | R108: =M108/Q108 -> 59.161577
A109: 19 Talcahuano | B109: Normalización 3°Etapa y Final Hospital Las Higueras, Talcahuano | C109: 591 | D109: Disminución partidas planta transitoria de hemodialisis | E109: Funcionalidad | F109: TERMINACIONES | G109: 0 | H109: 31867080 | I109: 0 | J109: =+G109-H109+I109 -> -31867080 | K109: en revisión | L109: 0 | M109: =+J109+L109 -> -31867080 | N109: ORD. 1449 | O109: Ord C4/3050 del 31-08-2022 | P109: 44502 | Q109: 30403.92 | R109: =+M109/Q109 -> -1048.1241
A110: 22 Araucanía Sur | B110: Normalizacion Hospital Villarrica | C110: Nota de Cambio N°81.15 | D110: Cambio ventanas plomadas | E110: Funcionalidad | F110: Terminaciones | G110: 1268313 | H110: 42895 | I110: 226807 | J110: =+G110-H110+I110 -> 1452225 | K110: 0 | L110: 0 | M110: =+J110+L110 -> 1452225 | N110: Ord. 1918 del 22.07.22 SSAS | O110: ORD. 2858 | P110: 44764 | Q110: 33330.45 | R110: =M110/Q110 -> 43.570519
A111: 22 Araucanía Sur | B111: Normalizacion Hospital Villarrica | C111: Nota de Cambio N°81.14 | D111: Sala tratamiento de agua | E111: Funcionalidad | F111: Instalaciones/Sanitaria | G111: 696874 | H111: 2451412 | I111: 2614876 | J111: =+G111-H111+I111 -> 860338 | K111: 0 | L111: 0 | M111: =+J111+L111 -> 860338 | N111: Ord. 1918 del 22.07.22 SSAS | O111: ORD. 2858 | P111: 44764 | Q111: 33330.45 | R111: =M111/Q111 -> 25.812373
A112: 22 Araucanía Sur | B112: Normalizacion Hospital Villarrica | C112: Nota de Cambio N°81.13 | D112: Pintura residuos sucios | E112: Funcionalidad | F112: Instalaciones/Sanitaria | G112: 5035287 | H112: 3935441 | J112: =+G112-H112+I112 -> 1099846 | K112: 0 | L112: 0 | M112: =+J112+L112 -> 1099846 | N112: Ord. 1918 del 22.07.22 SSAS | O112: ORD. 2858 | P112: 44764 | Q112: 33330.45 | R112: =M112/Q112 -> 32.998234
A113: 22 Araucanía Sur | B113: Normalizacion Hospital Villarrica | C113: Nota de Cambio N°81.12 | D113: Modificación en sala terapia ocupacional | E113: Funcionalidad | F113: Instalaciones/Sanitaria | G113: 118153 | I113: 37327 | J113: =+G113-H113+I113 -> 155480 | K113: 0 | L113: 0 | M113: =+J113+L113 -> 155480 | N113: Ord. 1918 del 22.07.22 SSAS | O113: ORD. 2858 | P113: 44764 | Q113: 33330.45 | R113: =M113/Q113 -> 4.6648035
A114: 22 Araucanía Sur | B114: Normalizacion Hospital Villarrica | C114: Nota de Cambio N°81.11 | D114: Modificación Reas | E114: AS/NTB | F114: Instalaciones/Sanitaria | G114: 4373914 | H114: 3807099 | J114: =+G114-H114+I114 -> 566815 | K114: 0 | L114: 0 | M114: =+J114+L114 -> 566815 | N114: Ord. 1918 del 22.07.22 SSAS | O114: ORD. 2858 | P114: 44764 | Q114: 33330.45 | R114: =M114/Q114 -> 17.005921
A115: 22 Araucanía Sur | B115: Normalizacion Hospital Villarrica | C115: Nota de Cambio N°81.10 | D115: Box Traumatología | E115: AS/NTB | F115: Terminaciones | G115: 30535 | I115: 756036 | J115: =+G115-H115+I115 -> 786571 | K115: 0 | L115: 0 | M115: =+J115+L115 -> 786571 | N115: Ord. 1918 del 22.07.22 SSAS | O115: ORD. 2858 | P115: 44764 | Q115: 33330.45 | R115: =M115/Q115 -> 23.599171
A116: 22 Araucanía Sur | B116: Normalizacion Hospital Villarrica | C116: Nota de Cambio N°81.09 | D116: Laboratorio Dental | E116: Errores de Diseño | F116: Terminaciones | G116: 5058943 | H116: 1582310 | I116: 1132649 | J116: =+G116-H116+I116 -> 4609282 | K116: 0 | L116: 0 | M116: =+J116+L116 -> 4609282 | N116: Ord. 1918 del 22.07.22 SSAS | O116: ORD. 2858 | P116: 44764 | Q116: 33330.45 | R116: =M116/Q116 -> 138.29042
...

Sheet Validaciones
A1: Servicio de Salud | B1: Clasificación: | C1: Partida:
A2: -Seleccionar- | B2: -Seleccionar- | C2: -Seleccionar-
A3: 01 Arica | B3: Errores de Diseño | C3: Obras Previas
A4: 02 Iquique | B4: Funcionalidad | C4: Obra Gruesa
A5: 03 Antofagasta | B5: Normativa (OGUC, Serviu, etc.) | C5: Terminaciones
A6: 04 Atacama | B6: AS/NTB | C6: Instalaciones/Eléctricas
A7: 05 Coquimbo | C7: Instalaciones/Sanitaria
A8: 06 Aconcagua | C8: Instalaciones/Gases Clínicos
A9: 07 Viña del Mar Quillota | C9: Instalaciones/Climatización
A10: 08 Valparaíso San Antonio | C10: Instalaciones/Gas
A11: 09 Metropolitano Norte | C11: Instalaciones/Control Central
A12: 10 Metropolitano Central | C12: Instalaciones/Seguridad
A13: 11 Metropolitano Oriente | C13: Instalaciones/Ascensores
A14: 12 Metropolitano Occidente | C14: Instalaciones/Corrientes Débiles
A15: 13 Metropolitano Sur | C15: Obras Exteriores
A16: 14 Metropolitano Sur Oriente
A17: 15 O'Higgins
A18: 16 Maule
A19: 17 Ñuble
A20: 18 Concepción
A21: 19 Talcahuano
A22: 20 Bío Bío
A23: 21 Arauco
A24: 22 Araucanía Sur
A25: 23 Araucanía Norte
A26: 24 Valdivia
A27: 25 Reloncaví
... A31: 29 Magallanes

Sheet 3_Validaciones
B1: Servicios de Salud | C1: Origen | D1: Partidas
B2: - SELECCIONAR - | C2: - SELECCIONAR - | D2: - SELECCIONAR -
B3: 01 Arica | C3: Funcionalidad | D3: Instalaciones
B4: 02 Iquique | C4: Errores de Diseño | D4: Instalaciones/Sanitaria
B5: 03 Antofagasta | C5: AS/NTB | D5: Instalaciones/Electricas
B6: 04 Atacama | C6: Normativa(OGUC,SERVIU,NTB,etc) | D6: Instalaciones/Gases Clinicos
B7: 05 Coquimbo | D7: Obra Gruesa
B8: 06 Aconcagua | D8: Terminaciones
B9: 07 Viña del Mar Quillota
B10: 08 Valparaíso San Antonio
B11: 09 Metropolitano Norte
B12: 10 Metropolitano Central
B13: 11 Metropolitano Oriente
B14: 12 Metropolitano Occidente
B15: 13 Metropolitano Sur
B16: 14 Metropolitano Sur Oriente
B17: 15 O'Higgins
B18: 16 Maule
B19: 17 Ñuble
B20: 18 Concepción
... B31: 29 Magallanes
